cal9000/__init__.py
cal9000/__main__.py
cal9000/command_bar.py
cal9000/config.py
cal9000/date.py
cal9000/dates.py
cal9000/events.py
cal9000/io.py
cal9000/render/__init__.py
cal9000/render/calendar.py
cal9000/render/day.py
cal9000/render/event_manager.py
cal9000/render/help.py
cal9000/render/main.py
cal9000/ui.py
cal9000-0.2.0.dist-info/entry_points.txt
cal9000-0.2.0.dist-info/METADATA
cal9000-0.2.0.dist-info/LICENSE
cal9000-0.2.0.dist-info/WHEEL
cal9000-0.2.0.dist-info/RECORD
